httpraw/__init__.py
httpraw/httpraw.py
http_raw-0.2.1.dist-info/LICENSE
http_raw-0.2.1.dist-info/METADATA
http_raw-0.2.1.dist-info/WHEEL
http_raw-0.2.1.dist-info/top_level.txt
http_raw-0.2.1.dist-info/RECORD
