Metadata-Version: 2.1
Name: http-raw
Version: 0.2.1
Summary: A library for better processing of raw data
Home-page: https://github.com/Buzz2d0/httpraw
Author: buzz
Author-email: admin@imipy.com
License: GPL
Keywords: http-raw
Platform: all
Classifier: Programming Language :: Python :: 3
Requires-Dist: requests
Requires-Dist: PySocks
